{
  "main": {
    "id": "439adb609467a8c5",
    "type": "split",
    "children": [
      {
        "id": "b744a91528f3b4ca",
        "type": "tabs",
        "children": [
          {
            "id": "69a6de6967a87857",
            "type": "leaf",
            "state": {
              "type": "pdf",
              "state": {
                "file": "GAL 1/PDFs/sistemas_de_ecuaciones_lineales.pdf"
              },
              "icon": "lucide-file-text",
              "title": "sistemas_de_ecuaciones_lineales"
            }
          }
        ]
      }
    ],
    "direction": "vertical"
  },
  "left": {
    "id": "710dc07f826331b2",
    "type": "split",
    "children": [
      {
        "id": "3c5a432e4a587982",
        "type": "tabs",
        "children": [
          {
            "id": "91e46512f1720447",
            "type": "leaf",
            "state": {
              "type": "file-explorer",
              "state": {
                "sortOrder": "alphabetical",
                "autoReveal": false
              },
              "icon": "lucide-folder-closed",
              "title": "Explorador de archivos"
            }
          },
          {
            "id": "b2510608e6bdd3ff",
            "type": "leaf",
            "state": {
              "type": "search",
              "state": {
                "query": "",
                "matchingCase": false,
                "explainSearch": false,
                "collapseAll": false,
                "extraContext": false,
                "sortOrder": "alphabetical"
              },
              "icon": "lucide-search",
              "title": "Buscar"
            }
          },
          {
            "id": "f5ff228a6c0857e0",
            "type": "leaf",
            "state": {
              "type": "bookmarks",
              "state": {},
              "icon": "lucide-bookmark",
              "title": "Marcadores"
            }
          }
        ]
      }
    ],
    "direction": "horizontal",
    "width": 203.5
  },
  "right": {
    "id": "5177a383b3682194",
    "type": "split",
    "children": [
      {
        "id": "a5afc65ff2723698",
        "type": "tabs",
        "children": [
          {
            "id": "c0df37ebb48a5c9f",
            "type": "leaf",
            "state": {
              "type": "backlink",
              "state": {
                "file": "GAL 1/PDFs/sistemas_de_ecuaciones_lineales.pdf",
                "collapseAll": false,
                "extraContext": false,
                "sortOrder": "alphabetical",
                "showSearch": false,
                "searchQuery": "",
                "backlinkCollapsed": false,
                "unlinkedCollapsed": true
              },
              "icon": "links-coming-in",
              "title": "Enlaces entrantes de sistemas_de_ecuaciones_lineales"
            }
          },
          {
            "id": "4457b89cc449bd4a",
            "type": "leaf",
            "state": {
              "type": "outgoing-link",
              "state": {
                "file": "GAL 1/PDFs/sistemas_de_ecuaciones_lineales.pdf",
                "linksCollapsed": true,
                "unlinkedCollapsed": true
              },
              "icon": "links-going-out",
              "title": "Enlaces salientes de sistemas_de_ecuaciones_lineales"
            }
          },
          {
            "id": "410cb78d0b3a730d",
            "type": "leaf",
            "state": {
              "type": "tag",
              "state": {
                "sortOrder": "frequency",
                "useHierarchy": true,
                "showSearch": false,
                "searchQuery": ""
              },
              "icon": "lucide-tags",
              "title": "Etiquetas"
            }
          },
          {
            "id": "c70d9a8501079976",
            "type": "leaf",
            "state": {
              "type": "outline",
              "state": {
                "file": "GAL 1/PDFs/sistemas_de_ecuaciones_lineales.pdf",
                "followCursor": false,
                "showSearch": false,
                "searchQuery": ""
              },
              "icon": "lucide-list",
              "title": "Esquema de sistemas_de_ecuaciones_lineales"
            }
          },
          {
            "id": "ad316d60edd2a77f",
            "type": "leaf",
            "state": {
              "type": "git-view",
              "state": {},
              "icon": "git-pull-request",
              "title": "Source Control"
            }
          }
        ],
        "currentTab": 4
      }
    ],
    "direction": "horizontal",
    "width": 200,
    "collapsed": true
  },
  "left-ribbon": {
    "hiddenItems": {
      "switcher:Abrir selector rápido": false,
      "graph:Abrir vista gráfica": false,
      "canvas:Crear nuevo lienzo": false,
      "daily-notes:Abrir la nota de hoy": false,
      "templates:Insertar plantilla": false,
      "command-palette:Abrir paleta de comandos": false,
      "obsidian-git:Open Git source control": false,
      "omnisearch:Omnisearch": false
    }
  },
  "active": "69a6de6967a87857",
  "lastOpenFiles": [
    "GAL 1/PDFs/Sistemas de ecuaciones lineales.md",
    "GAL 1/PDFs/sistemas_de_ecuaciones_lineales.pdf",
    "GAL 1/Sistema de ecuaciones.md",
    "GAL 1/PDFs",
    "Matemática Inicial/Semana 3/Razonamiento Lógico.md",
    "GAL 1",
    "Matemática Inicial/Semana 1/Operadores.md",
    "Matemática Inicial/Semana 3",
    "Matemática Inicial/Semana 2/Ecuaciones - Inecuaciones.md",
    "Matemática Inicial/Semana 2/Material Semana 2",
    "Matemática Inicial/Semana 2",
    "Matemática Inicial/PDFs M1/Libro Marilina Carena.md",
    "Matemática Inicial/Semana 1",
    "Matemática Inicial/PDFs M1",
    "Programacion I/PDFs P1/Práctico 6.md",
    "Matemática Inicial",
    "Programacion I/PDFs P1/Práctico 5.md",
    "Programacion I/Semana 5/Material Semana 5.md",
    "Programacion I/Semana 4/Material Semana 4.md",
    "Programacion I/Semana 4/Repetición (for).md",
    "Programacion I/Semana 4/Repetición Condicional.md",
    "Programacion I/Semana 2/Componentes Básicos.md",
    "Programacion I/Semana 3/Material Semana 3.md",
    "Programacion I/Semana 2/Material Semana 2.md",
    "Programacion I/PDFs P1/Guía teórica para Componentes básicos.md",
    "Programacion I/Semana 3/Estructuras de Control. Secuencia y Selección.md",
    "Programacion I/Semana 5",
    "Programacion I/PDFs P1/Práctico 4.md",
    "Programacion I/PDFs P1/Guía teórica para Repetición Condicional (while y repeat).md",
    "Programacion I/PDFs P1/Guía teórica para Repetición (for).md",
    "Programacion I/PDFs P1/Práctico 3.md",
    "Programacion I/PDFs P1/Práctico 2.md",
    "Programacion I/Images/Lectura_de_enteros.png",
    "Programacion I/PDFs P1/Guía teórica para Secuencia y Selección.md",
    "Programacion I/Semana 2/Entrada y Salida.md",
    "Programacion I/PDFs P1/Guía teórica para Entrada - Salida.md",
    "Programacion I/Images/Sintaxis_de_case.png",
    "Programacion I/Images/if-then-else.png",
    "Programacion I/Images/diagrama_la_secuencia.png",
    "Programacion I/Images/El_tipo_real.jpg",
    "Concepto_de_tipo 1.jpg",
    "Concepto_de_tipo.jpg",
    "Programacion I/Images/Concepto_de_tipo.jpg",
    "Programacion I/Images/Sintaxis-de-la-declaracion-de-variables .jpg",
    "Programacion I/Images/compilar-pascal 1.png"
  ]
}